drb/topics/landsat8/__init__.py
drb/topics/landsat8/_version.py
drb/topics/landsat8/cortex.yml
drb/topics/landsat8/libs/__init__.py
drb/topics/landsat8/libs/commons-compress-1.12.jar
drb/topics/landsat8/libs/drbx-cortex-topic-landsat-8-1.3.6.jar
drb/topics/landsat8/libs/drbx-impl-http-0.0.10.jar
drb/topics/landsat8/libs/drbx-impl-tar-1.0.9.jar
drb/topics/landsat8/libs/drbx-impl-text-1.0.5.jar
drb/topics/landsat8/libs/drbx-impl-tiff-1.2.3.jar
drb/topics/landsat8/libs/drbx-impl-zip-1.1.20.jar
drb/topics/landsat8/libs/imageio-ext-tiff-1.1.5.jar
drb/topics/landsat8/libs/imageio-ext-utilities-1.1.5.jar
drb/topics/landsat8/libs/jai_codec-1.1.3.jar
drb/topics/landsat8/libs/jai_core-1.1.3.jar
drb/topics/landsat8/libs/jai_imageio-1.1.jar
drb_topic_landsat8-1.2.0.dist-info/LICENCE.txt
drb_topic_landsat8-1.2.0.dist-info/METADATA
drb_topic_landsat8-1.2.0.dist-info/WHEEL
drb_topic_landsat8-1.2.0.dist-info/entry_points.txt
drb_topic_landsat8-1.2.0.dist-info/top_level.txt
drb_topic_landsat8-1.2.0.dist-info/RECORD
